{"is_source_file": false, "format": "", "description": "", "external_files": [], "external_methods": [], "published": [], "classes": [], "methods": [], "calls": [], "search-terms": ["flutter-tic-tac-toe-216745-216813", "README.md"], "state": 2, "file_id": 1, "knowledge_revision": 21, "git_revision": "68ffc81303a2685173290a9c39655a01c69d7900", "hash": "476f305dfb80501517cf97d59e4d4bad", "format-version": 4, "code-base-name": "tic_tac_toe_frontend", "filename": "README.md", "revision_history": [{"21": "68ffc81303a2685173290a9c39655a01c69d7900"}]}